ecmind_blue_client/__init__.py
ecmind_blue_client/blue_exception.py
ecmind_blue_client/client.py
ecmind_blue_client/const.py
ecmind_blue_client/dms_result.py
ecmind_blue_client/job.py
ecmind_blue_client/options.py
ecmind_blue_client/param.py
ecmind_blue_client/query_condition_field.py
ecmind_blue_client/query_condition_group.py
ecmind_blue_client/query_result_field.py
ecmind_blue_client/request_file.py
ecmind_blue_client/result.py
ecmind_blue_client/result_file.py
ecmind_blue_client/tcp_client.py
ecmind_blue_client/tcp_pool_client.py
ecmind_blue_client/rpc/__init__.py
ecmind_blue_client/rpc/api.py
ecmind_blue_client/rpc/async_api.py
ecmind_blue_client/rpc/sync_api.py
ecmind_blue_client-0.9.2.dist-info/LICENSE
ecmind_blue_client-0.9.2.dist-info/METADATA
ecmind_blue_client-0.9.2.dist-info/WHEEL
ecmind_blue_client-0.9.2.dist-info/top_level.txt
ecmind_blue_client-0.9.2.dist-info/RECORD
