Metadata-Version: 2.1
Name: ecmind-blue-client
Version: 0.9.2
Summary: A client wrapper for blue
Author-email: Roland Koller <info@ecmind.ch>, Ulrich Wohlfeil <info@ecmind.ch>, Anja Genser <info@ecmind.ch>
License: MIT License
Project-URL: Homepage, https://gitlab.ecmind.ch/open/ecmind_blue_client
Project-URL: Documentation, https://gitlab.ecmind.ch/open/ecmind_blue_client/-/wikis/home
Project-URL: Repository, https://gitlab.ecmind.ch/open/ecmind_blue_client.git
Project-URL: Issues, https://ecm.community/c/python/9
Classifier: Programming Language :: Python :: 3
Classifier: Operating System :: OS Independent
Classifier: Development Status :: 4 - Beta
Classifier: Intended Audience :: Developers
Classifier: Intended Audience :: System Administrators
Classifier: Topic :: System :: Archiving
Requires-Python: >=3.11
License-File: LICENSE
Provides-Extra: tcpclient
Requires-Dist: XmlElement>=0.3.1; extra == "tcpclient"
Provides-Extra: development
Requires-Dist: wheel; extra == "development"
Requires-Dist: build; extra == "development"
Requires-Dist: setuptools-scm; extra == "development"
Requires-Dist: twine; extra == "development"
Requires-Dist: black; extra == "development"
Requires-Dist: pylint; extra == "development"
Requires-Dist: pytest; extra == "development"
Provides-Extra: manage
Requires-Dist: ecmind-blue-client-manage; extra == "manage"
Provides-Extra: objdef
Requires-Dist: ecmind-blue-client-objdef; extra == "objdef"
Provides-Extra: portfolio
Requires-Dist: ecmind-blue-client-portfolio; extra == "portfolio"
Provides-Extra: tcp
Requires-Dist: XmlElement>=0.3.1; extra == "tcp"
Provides-Extra: workflow
Requires-Dist: ecmind-blue-client-workflow; extra == "workflow"
